{
    "name": "import_BB",
    "item_type": "Importer",
    "mapping": {
        "table_mappings": {
            "node": [
                {
                    "Mapping 1": {
                        "mapping": [
                            {
                                "map_type": "ObjectClass",
                                "position": "hidden",
                                "value": "node"
                            },
                            {
                                "map_type": "Object",
                                "position": 0
                            },
                            {
                                "map_type": "ObjectMetadata",
                                "position": "hidden"
                            }
                        ]
                    }
                }
            ],
            "demand": [
                {
                    "Mapping 1": {
                        "mapping": [
                            {
                                "map_type": "RelationshipClass",
                                "position": "hidden",
                                "value": "ts_grid__node__f"
                            },
                            {
                                "map_type": "RelationshipClassObjectClass",
                                "position": "hidden",
                                "value": "grid"
                            },
                            {
                                "map_type": "RelationshipClassObjectClass",
                                "position": "hidden",
                                "value": "node"
                            },
                            {
                                "map_type": "RelationshipClassObjectClass",
                                "position": "hidden",
                                "value": "ft"
                            },
                            {
                                "map_type": "Relationship",
                                "position": "hidden",
                                "value": "relationship"
                            },
                            {
                                "map_type": "RelationshipObject",
                                "position": "hidden",
                                "value": "grid",
                                "import_objects": true
                            },
                            {
                                "map_type": "RelationshipObject",
                                "position": -1,
                                "import_objects": true
                            },
                            {
                                "map_type": "RelationshipObject",
                                "position": "hidden",
                                "value": "f00",
                                "import_objects": true
                            },
                            {
                                "map_type": "RelationshipMetadata",
                                "position": "hidden"
                            },
                            {
                                "map_type": "ParameterDefinition",
                                "position": "hidden",
                                "value": "ts_influx"
                            },
                            {
                                "map_type": "Alternative",
                                "position": -2
                            },
                            {
                                "map_type": "ParameterValueMetadata",
                                "position": "hidden"
                            },
                            {
                                "map_type": "ParameterValueType",
                                "position": "hidden",
                                "value": "map"
                            },
                            {
                                "map_type": "ParameterValueIndex",
                                "position": 0
                            },
                            {
                                "map_type": "ExpandedValue",
                                "position": "hidden"
                            }
                        ]
                    }
                }
            ],
            "p_unit": [
                {
                    "Mapping 1": {
                        "mapping": [
                            {
                                "map_type": "ObjectClass",
                                "position": "hidden",
                                "value": "unit"
                            },
                            {
                                "map_type": "Object",
                                "position": 0
                            },
                            {
                                "map_type": "ObjectMetadata",
                                "position": "hidden"
                            },
                            {
                                "map_type": "ParameterDefinition",
                                "position": 1
                            },
                            {
                                "map_type": "Alternative",
                                "position": -1
                            },
                            {
                                "map_type": "ParameterValueMetadata",
                                "position": "hidden"
                            },
                            {
                                "map_type": "ParameterValue",
                                "position": "hidden"
                            }
                        ]
                    }
                }
            ],
            "node__unit__io": [
                {
                    "Mapping 1": {
                        "mapping": [
                            {
                                "map_type": "RelationshipClass",
                                "position": "hidden",
                                "value": "grid__node__unit__io"
                            },
                            {
                                "map_type": "RelationshipClassObjectClass",
                                "position": "hidden",
                                "value": "grid"
                            },
                            {
                                "map_type": "RelationshipClassObjectClass",
                                "position": "hidden",
                                "value": "node"
                            },
                            {
                                "map_type": "RelationshipClassObjectClass",
                                "position": "hidden",
                                "value": "unit"
                            },
                            {
                                "map_type": "RelationshipClassObjectClass",
                                "position": "hidden",
                                "value": "input_output"
                            },
                            {
                                "map_type": "Relationship",
                                "position": "hidden",
                                "value": "relationship"
                            },
                            {
                                "map_type": "RelationshipObject",
                                "position": "hidden",
                                "value": "grid"
                            },
                            {
                                "map_type": "RelationshipObject",
                                "position": 0
                            },
                            {
                                "map_type": "RelationshipObject",
                                "position": 1
                            },
                            {
                                "map_type": "RelationshipObject",
                                "position": 2
                            },
                            {
                                "map_type": "RelationshipMetadata",
                                "position": "hidden"
                            }
                        ]
                    }
                }
            ],
            "unit": [
                {
                    "Mapping 1": {
                        "mapping": [
                            {
                                "map_type": "ObjectClass",
                                "position": "hidden",
                                "value": "unit"
                            },
                            {
                                "map_type": "Object",
                                "position": 0
                            },
                            {
                                "map_type": "ObjectMetadata",
                                "position": "hidden"
                            }
                        ]
                    }
                }
            ],
            "commodity": [
                {
                    "Mapping 1": {
                        "mapping": [
                            {
                                "map_type": "ObjectClass",
                                "position": "hidden"
                            },
                            {
                                "map_type": "Object",
                                "position": "hidden"
                            },
                            {
                                "map_type": "ObjectMetadata",
                                "position": "hidden"
                            }
                        ]
                    }
                }
            ],
            "p_commodity_price": [
                {
                    "Mapping 1": {
                        "mapping": [
                            {
                                "map_type": "RelationshipClass",
                                "position": "hidden",
                                "value": "commodity"
                            },
                            {
                                "map_type": "RelationshipClassObjectClass",
                                "position": "hidden",
                                "value": "node"
                            },
                            {
                                "map_type": "Relationship",
                                "position": "hidden",
                                "value": "relationship"
                            },
                            {
                                "map_type": "RelationshipObject",
                                "position": -1,
                                "import_objects": true
                            },
                            {
                                "map_type": "RelationshipMetadata",
                                "position": "hidden"
                            },
                            {
                                "map_type": "ParameterDefinition",
                                "position": "hidden",
                                "value": "priceChange"
                            },
                            {
                                "map_type": "Alternative",
                                "position": 1
                            },
                            {
                                "map_type": "ParameterValueMetadata",
                                "position": "hidden"
                            },
                            {
                                "map_type": "ParameterValueType",
                                "position": "hidden",
                                "value": "map"
                            },
                            {
                                "map_type": "ParameterValueIndex",
                                "position": 0
                            },
                            {
                                "map_type": "ExpandedValue",
                                "position": "hidden"
                            }
                        ]
                    }
                }
            ],
            "capacityFactor": [
                {
                    "Mapping 1": {
                        "mapping": [
                            {
                                "map_type": "ObjectClass",
                                "position": "hidden"
                            },
                            {
                                "map_type": "Object",
                                "position": "hidden"
                            },
                            {
                                "map_type": "ObjectMetadata",
                                "position": "hidden"
                            }
                        ]
                    }
                }
            ],
            "reserveDemand": [
                {
                    "Mapping 1": {
                        "mapping": [
                            {
                                "map_type": "RelationshipClass",
                                "position": "hidden",
                                "value": "ts_restype__up_down__group"
                            },
                            {
                                "map_type": "RelationshipClassObjectClass",
                                "position": "hidden",
                                "value": "restype"
                            },
                            {
                                "map_type": "RelationshipClassObjectClass",
                                "position": "hidden",
                                "value": "up_down"
                            },
                            {
                                "map_type": "RelationshipClassObjectClass",
                                "position": "hidden",
                                "value": "group"
                            },
                            {
                                "map_type": "RelationshipClassObjectClass",
                                "position": "hidden",
                                "value": "f"
                            },
                            {
                                "map_type": "Relationship",
                                "position": "hidden",
                                "value": "relationship"
                            },
                            {
                                "map_type": "RelationshipObject",
                                "position": -2,
                                "import_objects": true
                            },
                            {
                                "map_type": "RelationshipObject",
                                "position": -3,
                                "import_objects": true
                            },
                            {
                                "map_type": "RelationshipObject",
                                "position": -1,
                                "import_objects": true
                            },
                            {
                                "map_type": "RelationshipObject",
                                "position": "hidden",
                                "value": "f00"
                            },
                            {
                                "map_type": "RelationshipMetadata",
                                "position": "hidden"
                            },
                            {
                                "map_type": "ParameterDefinition",
                                "position": "hidden",
                                "value": "reserveDemand"
                            },
                            {
                                "map_type": "Alternative",
                                "position": 0
                            },
                            {
                                "map_type": "ParameterValueMetadata",
                                "position": "hidden"
                            },
                            {
                                "map_type": "ParameterValueType",
                                "position": "hidden",
                                "value": "map"
                            },
                            {
                                "map_type": "ParameterValueIndex",
                                "position": 1
                            },
                            {
                                "map_type": "ExpandedValue",
                                "position": "hidden"
                            }
                        ]
                    }
                }
            ],
            "unit_ts": [
                {
                    "Mapping 1": {
                        "mapping": [
                            {
                                "map_type": "RelationshipClass",
                                "position": "hidden",
                                "value": "unit_ts"
                            },
                            {
                                "map_type": "RelationshipClassObjectClass",
                                "position": "hidden",
                                "value": "unit"
                            },
                            {
                                "map_type": "Relationship",
                                "position": "hidden",
                                "value": "relationship"
                            },
                            {
                                "map_type": "RelationshipObject",
                                "position": 0,
                                "import_objects": true
                            },
                            {
                                "map_type": "RelationshipMetadata",
                                "position": "hidden"
                            },
                            {
                                "map_type": "ParameterDefinition",
                                "position": 2
                            },
                            {
                                "map_type": "Alternative",
                                "position": 1
                            },
                            {
                                "map_type": "ParameterValueMetadata",
                                "position": "hidden"
                            },
                            {
                                "map_type": "ParameterValueType",
                                "position": "hidden",
                                "value": "map"
                            },
                            {
                                "map_type": "ParameterValueIndex",
                                "position": 3
                            },
                            {
                                "map_type": "ExpandedValue",
                                "position": 4
                            }
                        ]
                    }
                }
            ]
        },
        "table_options": {
            "node": {},
            "demand": {},
            "p_unit": {},
            "node__unit__io": {},
            "unit": {},
            "commodity": {},
            "p_commodity_price": {},
            "capacityFactor": {},
            "reserveDemand": {},
            "unit_ts": {}
        },
        "table_types": {
            "node": {
                "0": "string"
            },
            "demand": {
                "0": "string",
                "1": "float"
            },
            "p_unit": {
                "0": "string",
                "1": "string",
                "2": "float",
                "3": "float"
            },
            "node__unit__io": {
                "0": "string",
                "1": "string",
                "2": "string"
            },
            "unit": {
                "0": "string"
            },
            "commodity": {
                "0": "string"
            },
            "p_commodity_price": {
                "0": "string",
                "1": "string",
                "2": "float"
            },
            "reserveDemand": {
                "0": "string",
                "1": "string",
                "2": "float"
            },
            "capacityFactor": {
                "0": "string",
                "1": "string",
                "2": "string",
                "3": "string",
                "4": "string"
            },
            "unit_ts": {
                "0": "string",
                "1": "string",
                "2": "string",
                "3": "string",
                "4": "float"
            }
        },
        "table_row_types": {
            "demand": {
                "1": "string",
                "0": "string"
            },
            "reserveDemand": {
                "1": "string",
                "2": "string",
                "0": "string"
            },
            "p_unit": {
                "1": "string"
            }
        },
        "selected_tables": [
            "Select All",
            "demand",
            "node__unit__io",
            "node",
            "unit",
            "commodity",
            "p_commodity_price",
            "capacityFactor",
            "reserveDemand",
            "unit_ts",
            "p_unit"
        ],
        "source_type": "ExcelConnector"
    },
    "description": ""
}